genu-0.1.4.dist-info/licenses/LICENSE
tests/__init__.py
tests/test_cli.py
uuid_cli/__init__.py
uuid_cli/cli.py
genu-0.1.4.dist-info/METADATA
genu-0.1.4.dist-info/WHEEL
genu-0.1.4.dist-info/entry_points.txt
genu-0.1.4.dist-info/top_level.txt
genu-0.1.4.dist-info/RECORD
