Metadata-Version: 2.4
Name: genu
Version: 0.1.4
Summary: A CLI tool to generate UUIDs of different versions.
Home-page: https://github.com/jeasoft/genu
Author: Jearel Alcantara
Author-email: Jearel Alcantara <jeasoft@gmail.com>
License: MIT
Requires-Python: >=3.9
License-File: LICENSE
Provides-Extra: uuid7
Requires-Dist: uuid6; extra == "uuid7"
Dynamic: author
Dynamic: home-page
Dynamic: license-file
Dynamic: requires-python
